Metadata-Version: 2.1
Name: matrixprofile
Version: 1.1.10
Summary: An open source time series data mining library based on Matrix Profile algorithms.
Home-page: https://github.com/matrix-profile-foundation/matrixprofile
Author: Matrix Profile Foundation
Author-email: tylerwmarrs@gmail.com
License: UNKNOWN
Project-URL: Source Code, https://github.com/matrix-profile-foundation/matrixprofile
Project-URL: Matrix Profile Foundation, https://matrixprofile.org
Keywords: matrix profile time series discord motif analysis data science anomaly pattern
Platform: UNKNOWN
Classifier: Programming Language :: Python :: 2
Classifier: Programming Language :: Python :: 3
Classifier: License :: OSI Approved :: Apache Software License
Classifier: Intended Audience :: Science/Research
Classifier: Intended Audience :: Information Technology
Classifier: Intended Audience :: Developers
Classifier: Operating System :: MacOS
Classifier: Operating System :: Microsoft :: Windows
Classifier: Operating System :: POSIX
Classifier: Topic :: Software Development
Classifier: Topic :: Scientific/Engineering
Requires-Dist: numpy (>=1.16.2)
Requires-Dist: matplotlib (>=3.0.3)
Requires-Dist: protobuf (==3.11.2)
Requires-Dist: scipy (<2.0.0,>=1.3.2)
